pSock/__init__.py
pSock/_utils.py
pSock-1.3.6.dist-info/LICENSE
pSock-1.3.6.dist-info/METADATA
pSock-1.3.6.dist-info/WHEEL
pSock-1.3.6.dist-info/top_level.txt
pSock-1.3.6.dist-info/RECORD
