Metadata-Version: 2.1
Name: pSock
Version: 1.3.6
Summary: pSock is a socket / threading module that helps developers and students to approach Server-Client creation and much more.
Home-page: UNKNOWN
Author: Andrea Vaccaro (ANDRVV)
License: BSD 3 License
Keywords: python,socket,threading,server,client
Platform: UNKNOWN
Classifier: Development Status :: 1 - Planning
Classifier: Intended Audience :: Developers
Classifier: Programming Language :: Python :: 3
Classifier: Operating System :: Unix
Classifier: Operating System :: MacOS :: MacOS X
Classifier: Operating System :: Microsoft :: Windows
License-File: LICENSE
